myfeeds_ai/__init__.py
myfeeds_ai/config/__init__.py
myfeeds_ai/data_feeds/Data_Feeds__Files.py
myfeeds_ai/data_feeds/Data_Feeds__Parser.py
myfeeds_ai/data_feeds/Data_Feeds__S3_DB.py
myfeeds_ai/data_feeds/Data_Feeds__S3__Key_Generator.py
myfeeds_ai/data_feeds/Data_Feeds__Shared_Constants.py
myfeeds_ai/data_feeds/__init__.py
myfeeds_ai/data_feeds/models/Model__Data_Feeds__Prompt.py
myfeeds_ai/data_feeds/models/Model__Data_Feeds__Providers.py
myfeeds_ai/data_feeds/models/Model__Data_Feeds__Raw_Data.py
myfeeds_ai/data_feeds/models/__init__.py
myfeeds_ai/fast_api/Data_Feeds__Fast_API.py
myfeeds_ai/fast_api/__init__.py
myfeeds_ai/fast_api/admin/Admin__Fast_API.py
myfeeds_ai/fast_api/admin/__init__.py
myfeeds_ai/fast_api/admin/routes/Routes__Admin__Setup.py
myfeeds_ai/fast_api/admin/routes/Routes__Debug.py
myfeeds_ai/fast_api/admin/routes/__init__.py
myfeeds_ai/fast_api/public_data/LLM_Cache__Fast_API.py
myfeeds_ai/fast_api/public_data/Public_Data__Fast_API.py
myfeeds_ai/fast_api/public_data/__init__.py
myfeeds_ai/fast_api/public_data/routes/Routes__LLM_Cache__Data.py
myfeeds_ai/fast_api/public_data/routes/Routes__Public__Hacker_News.py
myfeeds_ai/fast_api/public_data/routes/Routes__Public__Personas.py
myfeeds_ai/fast_api/public_data/routes/__init__.py
myfeeds_ai/fast_api/routes/Routes__Info.py
myfeeds_ai/fast_api/routes/__init__.py
myfeeds_ai/lambdas/__init__.py
myfeeds_ai/lambdas/handler.py
myfeeds_ai/mgraphs/__init__.py
myfeeds_ai/mgraphs/articles_index/__init__.py
myfeeds_ai/mgraphs/articles_index/actions/MGraph__Articles__Index.py
myfeeds_ai/mgraphs/articles_index/actions/__init__.py
myfeeds_ai/mgraphs/articles_index/schemas/Schema__Article__Index__Node.py
myfeeds_ai/mgraphs/articles_index/schemas/Schema__Article__Index__Node__Data.py
myfeeds_ai/mgraphs/articles_index/schemas/Schema__Article__Index__Types.py
myfeeds_ai/mgraphs/articles_index/schemas/__init__.py
myfeeds_ai/mgraphs/articles_timeline/__init__.py
myfeeds_ai-1.112.0.dist-info/LICENSE
myfeeds_ai-1.112.0.dist-info/METADATA
myfeeds_ai-1.112.0.dist-info/WHEEL
myfeeds_ai-1.112.0.dist-info/RECORD
