Metadata-Version: 2.3
Name: myfeeds_ai
Version: 1.112.0
Summary: MyFeeds.ai
License: Apache 2.0
Author: Dinis Cruz
Author-email: dinis.cruz@owasp.org
Requires-Python: >=3.11,<4.0
Classifier: License :: Other/Proprietary License
Classifier: Programming Language :: Python :: 3
Classifier: Programming Language :: Python :: 3.11
Classifier: Programming Language :: Python :: 3.12
Classifier: Programming Language :: Python :: 3.13
Requires-Dist: bs4
Requires-Dist: httpx
Requires-Dist: mangum
Requires-Dist: mgraph-db
Requires-Dist: osbot-aws
Requires-Dist: osbot-fast-api
Requires-Dist: osbot-local-stack
Requires-Dist: osbot-utils
Requires-Dist: pillow
Requires-Dist: uvicorn
Project-URL: Homepage, https://github.com/the-cyber-boardroom/myfeeds_ai
Project-URL: Repository, https://github.com/the-cyber-boardroom/myfeeds_ai
